malac/utils/__init__.py
malac/utils/date.py
malac/utils/fhirpath.py
malac_utils-1.2.0.dist-info/LICENSE
malac_utils-1.2.0.dist-info/METADATA
malac_utils-1.2.0.dist-info/WHEEL
malac_utils-1.2.0.dist-info/top_level.txt
malac_utils-1.2.0.dist-info/RECORD
