Metadata-Version: 2.1
Name: malac-utils
Version: 1.2.0
Summary: Mapping Language Compiler Utils
Author-email: cdeHealth-Team <contact-project+cdehealth-malac-hd-52276676-issue-@incoming.gitlab.com>
Project-URL: Homepage, https://gitlab.com/cdehealth/malac-hd
Project-URL: Documentation, https://gitlab.com/cdehealth/malac-hd
Project-URL: Release notes, https://gitlab.com/cdehealth/malac-hd/-/releases
Project-URL: Source, https://gitlab.com/cdehealth/malac-hd
Project-URL: Tracker, https://gitlab.com/cdehealth/malac-hd/-/issues
Classifier: Development Status :: 5 - Production/Stable
Classifier: Environment :: Console
Classifier: Intended Audience :: Information Technology
Classifier: Intended Audience :: Healthcare Industry
Classifier: Intended Audience :: Developers
Classifier: Intended Audience :: Science/Research
Classifier: License :: OSI Approved :: GNU Lesser General Public License v3 (LGPLv3)
Classifier: Natural Language :: English
Classifier: Operating System :: OS Independent
Classifier: Programming Language :: Python
Classifier: Topic :: Software Development :: Code Generators
Classifier: Topic :: Software Development :: Libraries
Requires-Python: >=3.10
License-File: LICENSE
Requires-Dist: python-dateutil>=2.8.2
